{
	"XDRBuiltInField": false,
	"aliasTo": "",
	"aliases": null,
	"associatedToAll": false,
	"associatedTypes": [
		"Cortex XDR Port Scan",
		"Cortex XDR - XCLOUD",
		"Cortex XDR - XCLOUD Cryptomining",
		"Cortex XDR Device Control Violations",
		"Cortex XDR Disconnected endpoints",
		"Cortex XDR Incident"
	],
	"autoCompleteTags": null,
	"breachScript": "",
	"cacheVersn": 0,
	"caseInsensitive": true,
	"cliName": "xdrriskyhostcount",
	"closeForm": false,
	"columns": null,
	"content": true,
	"defaultRows": null,
	"definitionId": "",
	"description": "The number of hosts identified as risky by Cortex XDR.",
	"editForm": true,
	"fieldCalcScript": "",
	"fromServerVersion": "6.5.0",
	"group": 0,
	"hidden": false,
	"id": "incident_xdrriskyhostcount",
	"ipVersion": "",
	"isReadOnly": false,
	"itemVersion": "6.0.4",
	"locked": false,
	"mergeStrategy": "",
	"name": "XDR Risky Host Count",
	"neverSetAsRequired": false,
	"openEnded": false,
	"orgType": "",
	"ownerOnly": false,
	"packID": "CortexXDR",
	"packName": "Cortex XDR by Palo Alto Networks",
	"packPropagationLabels": [
		"all"
	],
	"placeholder": "",
	"pretty_name": "XDR Risky Host Count",
	"propagationLabels": [],
	"required": false,
	"runScriptAfterUpdate": false,
	"script": "",
	"selectValues": null,
	"selectValuesMap": null,
	"sla": 0,
	"system": false,
	"systemAssociatedTypes": null,
	"template": "",
	"threshold": 72,
	"toServerVersion": "",
	"type": "number",
	"unmapped": false,
	"unsearchable": false,
	"useAsKpi": false,
	"validatedError": "",
	"validationRegex": "",
	"version": -1,
	"x2_fields": ""
}