{
	"XDRBuiltInField": false,
	"aliasTo": "",
	"aliases": null,
	"associatedToAll": false,
	"associatedTypes": [
		"Google Drive Activity"
	],
	"autoCompleteTags": null,
	"breachScript": "",
	"cacheVersn": 0,
	"caseInsensitive": true,
	"cliName": "googledriveactivityremovedpermissions",
	"closeForm": false,
	"columns": [
		{
			"displayName": "Role",
			"fieldCalcScript": "",
			"isDefault": true,
			"isReadOnly": false,
			"key": "role",
			"orgType": "shortText",
			"required": false,
			"script": "",
			"selectValues": null,
			"type": "shortText",
			"width": 150
		},
		{
			"displayName": "Allow Discovery",
			"fieldCalcScript": "",
			"isDefault": true,
			"isReadOnly": false,
			"key": "allowdiscovery",
			"orgType": "boolean",
			"required": false,
			"script": "",
			"selectValues": null,
			"type": "boolean",
			"width": 150
		},
		{
			"displayName": "Person Name",
			"fieldCalcScript": "",
			"isDefault": true,
			"isReadOnly": false,
			"key": "personname",
			"orgType": "shortText",
			"required": false,
			"script": "",
			"selectValues": null,
			"type": "shortText",
			"width": 150
		},
		{
			"displayName": "Is Current User",
			"fieldCalcScript": "",
			"isDefault": true,
			"isReadOnly": false,
			"key": "iscurrentuser",
			"orgType": "boolean",
			"required": false,
			"script": "",
			"selectValues": null,
			"type": "boolean",
			"width": 150
		},
		{
			"displayName": "Is Deleted User",
			"fieldCalcScript": "",
			"isDefault": true,
			"isReadOnly": false,
			"key": "isdeleteduser",
			"orgType": "boolean",
			"required": false,
			"script": "",
			"selectValues": null,
			"type": "boolean",
			"width": 150
		},
		{
			"displayName": "Is Unknown User",
			"fieldCalcScript": "",
			"isDefault": true,
			"isReadOnly": false,
			"key": "isunknownuser",
			"orgType": "boolean",
			"required": false,
			"script": "",
			"selectValues": null,
			"type": "boolean",
			"width": 150
		},
		{
			"displayName": "Group Email",
			"fieldCalcScript": "",
			"isDefault": true,
			"isReadOnly": false,
			"key": "groupemail",
			"orgType": "shortText",
			"required": false,
			"script": "",
			"selectValues": null,
			"type": "shortText",
			"width": 150
		},
		{
			"displayName": "Group Title",
			"fieldCalcScript": "",
			"isDefault": true,
			"isReadOnly": false,
			"key": "grouptitle",
			"orgType": "shortText",
			"required": false,
			"script": "",
			"selectValues": null,
			"type": "shortText",
			"width": 150
		},
		{
			"displayName": "Domain Name",
			"fieldCalcScript": "",
			"isDefault": true,
			"isReadOnly": false,
			"key": "domainname",
			"orgType": "shortText",
			"required": false,
			"script": "",
			"selectValues": null,
			"type": "shortText",
			"width": 150
		},
		{
			"displayName": "Is Anyone",
			"fieldCalcScript": "",
			"isDefault": true,
			"isReadOnly": false,
			"key": "isanyone",
			"orgType": "boolean",
			"required": false,
			"script": "",
			"selectValues": null,
			"type": "boolean",
			"width": 150
		}
	],
	"content": true,
	"defaultRows": [
		{},
		{},
		{}
	],
	"definitionId": "",
	"description": "The set of permissions removed by this change.",
	"editForm": true,
	"fieldCalcScript": "",
	"fromServerVersion": "5.0.0",
	"group": 0,
	"hidden": false,
	"id": "incident_googledriveactivityremovedpermissions",
	"ipVersion": "",
	"isReadOnly": false,
	"itemVersion": "1.2.45",
	"locked": false,
	"mergeStrategy": "",
	"name": "Google Drive Activity Removed Permissions",
	"neverSetAsRequired": false,
	"openEnded": false,
	"orgType": "grid",
	"ownerOnly": false,
	"packID": "GoogleDrive",
	"packName": "Google Drive",
	"packPropagationLabels": [
		"all"
	],
	"placeholder": "",
	"pretty_name": "",
	"propagationLabels": [],
	"required": false,
	"runScriptAfterUpdate": false,
	"script": "",
	"selectValues": null,
	"selectValuesMap": null,
	"sla": 0,
	"system": false,
	"systemAssociatedTypes": null,
	"template": "",
	"threshold": 72,
	"toServerVersion": "",
	"type": "grid",
	"unmapped": false,
	"unsearchable": false,
	"useAsKpi": false,
	"validatedError": "",
	"validationRegex": "",
	"version": -1,
	"x2_fields": ""
}